pyrefworks/__init__.py
pyrefworks/pyrefworks.py
pyrefworks/__pycache__/__init__.cpython-36.pyc
pyrefworks/__pycache__/pyrefworks.cpython-36.pyc
pyrefworks-0.0.1.dist-info/LICENSE
pyrefworks-0.0.1.dist-info/METADATA
pyrefworks-0.0.1.dist-info/WHEEL
pyrefworks-0.0.1.dist-info/top_level.txt
pyrefworks-0.0.1.dist-info/RECORD
